mved/__init__.py
mved/_version.py
mved/colors.py
mved/editor.py
mved/files.py
mved/fsbase.py
mved/fscache.py
mved/menu.py
mved/realfs.py
mved/utils.py
mved-0.7.3.data/data/share/vim/vimfiles/ftdetect/mved.vim
mved-0.7.3.data/data/share/vim/vimfiles/syntax/mved.vim
mved-0.7.3.dist-info/AUTHORS
mved-0.7.3.dist-info/LICENSE
mved-0.7.3.dist-info/METADATA
mved-0.7.3.dist-info/WHEEL
mved-0.7.3.dist-info/entry_points.txt
mved-0.7.3.dist-info/top_level.txt
mved-0.7.3.dist-info/RECORD
